{
  "id": "381sxrgc77",
  "category": "variety",
  "title": "お笑いの日２０２０",
  "fullTitle": "お笑いの日２０２０",
  "detail": "総勢１２６名が集結するお笑いだけの８時間生放送！☆総合ＭＣはダウンタウン☆\r\n今をときめく第７世代から超実力派まで登場のネタ祭り！笑いの力で日本中を元気に！\n◇番組内容\n総勢１２６名が集結するお笑いだけの８時間生放送！\r\n☆総合ＭＣはダウンタウン☆\r\n↑↑↑↑↑↑↑↑↑↑↑\r\n長時間生放送は２３年ぶり！\r\n☆今をときめく第７世代芸人から言わずもしれた超実力派芸人まで続々登場！！\r\nこの日限りの書き下ろしネタから超豪華SPコラボまで８時間ぶっ通し怒涛のネタ祭り！！\r\nこんな時だからこそ“笑いの力で日本中を元気に！”\r\n\n◇番組内容２\n☆２時からは音ネタフェス☆\r\n音ネタのみの９０分！\r\n書き下ろしＳＰコラボネタを披露\r\n☆広瀬香美×どぶろっく\r\n☆清塚信也×ロバート\r\n☆Creepy Nuts×ラップ大好き芸人\r\n☆渡辺直美×ハライチ岩井　他\n◇番組内容３\n☆３時３０分ごろからはベスト・オブ・ザ・ドリームマッチ☆\r\n「松本×トシ漫才」や「浜田×ロンブー淳コント」など\r\n第7世代が衝撃を受けたネタを発表！\r\nダウンタウン＆さまぁ～ずにNG無しの生質問をぶつける！\n◇番組内容４\n☆４時３０分ごろからはザ・ベストワン ☆\r\n今最もベストな芸人がベストなネタを披露するネタの祭典！\r\n新星から実力派まで一挙集結！\r\nオープニングスペシャルアクトで\r\n野村萬斎が登場！\r\nダウンタウンも\r\n\n◇出演者\n【総合ＭＣ】\r\nダウンタウン（浜田雅功＆松本人志）\r\n【ＭＣ】\r\n笑福亭鶴瓶\r\n今田耕司\r\n新木優子\r\n【出演】\r\nさまぁ～ず（大竹一樹＆三村マサカズ）\r\n☆☆☆☆☆☆☆☆☆☆☆☆☆☆☆\r\nあばれる君\r\nAMEMIYA\r\nEXIT\r\n岩井勇気（ハライチ）\r\nエイトブリッジ\r\nオジンオズボーン\r\nかまいたち\r\nカミナリ\r\n清塚信也\r\nくっきー！（野性爆弾）\r\n久保田かずのぶ（とろサーモン）\r\nCreepy Nuts\r\nクロスバー直撃\r\n\n◇出演者２\nさや香\r\n３時のヒロイン\r\nシャンプーハット\r\n衝撃デリバリー\r\nジョイマン\r\nchelmico\r\nチョコレートプラネット\r\nテツandトモ\r\nＴＯＫＵ\r\nとにかく明るい安村\r\nどぶろっく\r\nドランクドラゴン\r\n\n◇出演者３\n永野\r\nNON STYLE\r\nバイきんぐ\r\nハナコ\r\nはなわ\r\nビスケットブラザーズ\r\nヒロカズ劇場\r\n広瀬香美\r\nフワちゃん\r\nぺこぱ\r\nヘンダーソン\r\nミキ\r\nMr.マリック\r\n\n◇出演者４\n宮下草薙\r\nゆりやんレトリィバァ\r\n四千頭身\r\nレイザーラモンRG\r\nロッチ\r\nロバート\r\n渡辺直美\r\n笑い飯\r\nわらふぢなるお\r\n\n◇スタッフ\nチーフプロデューサー／坂本義幸\r\n総合演出／浜田諒介\r\n\n◇オリジナルグッズ\n☆お笑いの日オリジナルグッズ発売中☆\r\nくっきー！デザインのＴシャツからマグカップ、マスクなど\r\n完全オリジナルグッズが期間限定で発売中！\r\nさらに！放送時間内限定販売グッズも！\r\n☆詳しくは番組公式ページまで☆\r\n↓↓↓↓またはこちら↓↓↓↓\r\nhttps://ishop.tbs.co.jp/tbs/org/variety/owaraiday/\r\n\n◇公式ページ\n☆HP\r\nhttps://www.tbs.co.jp/owaraiday/\r\n☆Instagram\r\nowaraiday\r\n☆Twitter\r\n@owaraiday\r\n『ザ・ベストワン』\r\n☆Twitter\r\n@thebestone_tbs\r\n\n◇おことわり\n番組の内容と放送時間は変更になる可能性があります。",
  "start": 1601096400000,
  "end": 1601114400000,
  "seconds": 18000,
  "description": "総勢１２６名が集結するお笑いだけの８時間生放送！☆総合ＭＣはダウンタウン☆\r\n今をときめく第７世代から超実力派まで登場のネタ祭り！笑いの力で日本中を元気に！",
  "extra": {
    "番組内容": "総勢１２６名が集結するお笑いだけの８時間生放送！\r\n☆総合ＭＣはダウンタウン☆\r\n↑↑↑↑↑↑↑↑↑↑↑\r\n長時間生放送は２３年ぶり！\r\n☆今をときめく第７世代芸人から言わずもしれた超実力派芸人まで続々登場！！\r\nこの日限りの書き下ろしネタから超豪華SPコラボまで８時間ぶっ通し怒涛のネタ祭り！！\r\nこんな時だからこそ“笑いの力で日本中を元気に！”\r\n",
    "番組内容２": "☆２時からは音ネタフェス☆\r\n音ネタのみの９０分！\r\n書き下ろしＳＰコラボネタを披露\r\n☆広瀬香美×どぶろっく\r\n☆清塚信也×ロバート\r\n☆Creepy Nuts×ラップ大好き芸人\r\n☆渡辺直美×ハライチ岩井　他",
    "番組内容３": "☆３時３０分ごろからはベスト・オブ・ザ・ドリームマッチ☆\r\n「松本×トシ漫才」や「浜田×ロンブー淳コント」など\r\n第7世代が衝撃を受けたネタを発表！\r\nダウンタウン＆さまぁ～ずにNG無しの生質問をぶつける！",
    "番組内容４": "☆４時３０分ごろからはザ・ベストワン ☆\r\n今最もベストな芸人がベストなネタを披露するネタの祭典！\r\n新星から実力派まで一挙集結！\r\nオープニングスペシャルアクトで\r\n野村萬斎が登場！\r\nダウンタウンも\r\n",
    "出演者": "【総合ＭＣ】\r\nダウンタウン（浜田雅功＆松本人志）\r\n【ＭＣ】\r\n笑福亭鶴瓶\r\n今田耕司\r\n新木優子\r\n【出演】\r\nさまぁ～ず（大竹一樹＆三村マサカズ）\r\n☆☆☆☆☆☆☆☆☆☆☆☆☆☆☆\r\nあばれる君\r\nAMEMIYA\r\nEXIT\r\n岩井勇気（ハライチ）\r\nエイトブリッジ\r\nオジンオズボーン\r\nかまいたち\r\nカミナリ\r\n清塚信也\r\nくっきー！（野性爆弾）\r\n久保田かずのぶ（とろサーモン）\r\nCreepy Nuts\r\nクロスバー直撃\r\n",
    "出演者２": "さや香\r\n３時のヒロイン\r\nシャンプーハット\r\n衝撃デリバリー\r\nジョイマン\r\nchelmico\r\nチョコレートプラネット\r\nテツandトモ\r\nＴＯＫＵ\r\nとにかく明るい安村\r\nどぶろっく\r\nドランクドラゴン\r\n",
    "出演者３": "永野\r\nNON STYLE\r\nバイきんぐ\r\nハナコ\r\nはなわ\r\nビスケットブラザーズ\r\nヒロカズ劇場\r\n広瀬香美\r\nフワちゃん\r\nぺこぱ\r\nヘンダーソン\r\nミキ\r\nMr.マリック\r\n",
    "出演者４": "宮下草薙\r\nゆりやんレトリィバァ\r\n四千頭身\r\nレイザーラモンRG\r\nロッチ\r\nロバート\r\n渡辺直美\r\n笑い飯\r\nわらふぢなるお\r\n",
    "スタッフ": "チーフプロデューサー／坂本義幸\r\n総合演出／浜田諒介\r\n",
    "オリジナルグッズ": "☆お笑いの日オリジナルグッズ発売中☆\r\nくっきー！デザインのＴシャツからマグカップ、マスクなど\r\n完全オリジナルグッズが期間限定で発売中！\r\nさらに！放送時間内限定販売グッズも！\r\n☆詳しくは番組公式ページまで☆\r\n↓↓↓↓またはこちら↓↓↓↓\r\nhttps://ishop.tbs.co.jp/tbs/org/variety/owaraiday/\r\n",
    "公式ページ": "☆HP\r\nhttps://www.tbs.co.jp/owaraiday/\r\n☆Instagram\r\nowaraiday\r\n☆Twitter\r\n@owaraiday\r\n『ザ・ベストワン』\r\n☆Twitter\r\n@thebestone_tbs\r\n",
    "おことわり": "番組の内容と放送時間は変更になる可能性があります。\r\n"
  },
  "channel": {
    "type": "GR",
    "channel": "9",
    "name": "ＴＢＳ１",
    "id": "1i5727s",
    "sid": 1048,
    "nid": 32739,
    "hasLogoData": true,
    "n": 22
  },
  "subTitle": "",
  "episode": null,
  "flags": []
}
