{
  "id": "381sxrfxa2",
  "category": "music",
  "title": "音楽の日",
  "fullTitle": "音楽の日[字][デ]",
  "detail": "音楽の日は第二部も引き続き「汗」をテーマに５時間１５分の生放送！様々なアーティストがメドレーやカバーに参加！汗が光る灼熱のステージをお届け！！\n◇番組内容①\n第二部も引き続き「汗」をテーマに５時間１５分の生放送！「音楽の日」でしか見られないスペシャルメドレーやコラボレーションが盛りだくさん！！！\n◇番組内容②\n「ノンストップ灼熱うたリレー」では倖田來未の代表曲「キューティーハニー」から始まり、\r\nCHEMISTRY や HY、SHISHAMOなどが自身の大ヒットソングを熱く歌う！！\r\n\n◇番組内容③\n「夏うた全力カバーリレー」では日本人なら誰もが知っている夏の名曲をＡＫＢ４８や乃木坂４６ 、ゴールデンボンバー、そして人気急上昇中の s**t kingz （シットキングス）などが全力でカバー！\r\n\n◇番組内容④\n日本各地で活躍しているあのアーティストの皆さんも\r\nこの日のために赤坂に大集合し真夏の夜に熱いステージを披露！\r\n日本中の頑張る「汗」への応援歌をお届けします！\r\n\n◇出演者①\nAI\r\nIZ＊ONE\r\n藍井エイル\r\nAqours\r\n足立佳奈\r\nE-girls\r\n家入レオ\r\n内田雄馬\r\nウルフルズ\r\nAKB48\r\n\n◇出演者②\nHY\r\nA.B.C-Z\r\nSTU48\r\nエドガー・サリヴァン\r\nOnly this time\r\n木村カエラ\r\n倉木麻衣\r\nKREVA\r\nCHEMISTRY\r\n倖田來未\r\n\n◇出演者③\nゴールデンボンバー\r\nSaucy Dog\r\nザ・コインロッカーズ\r\nThe Super Ball\r\nTHE RAMPAGE from EXILE TRIBE\r\n\n◇出演者④\nサンプラザ中野くん\r\nSEAMO\r\nGENERATIONS from EXILE TRIBE\r\nSHISHAMO\r\ns**t kingz\r\n\n◇出演者⑤\nジャニーズWEST\r\nSuperfly\r\nスカイピース\r\n鈴木愛理\r\nChuning Candy\r\nD-51\r\nDRUM TAO\r\n中川翔子\r\n西川貴教\r\nnobodyknows+\r\n\n◇出演者⑥\n乃木坂46\r\nHOWL BE QUIET\r\nPerfume\r\nBALLISTIK BOYZ from EXILE TRIBE\r\nHAN-KUN\r\n日向坂46\r\nファンキー加藤\r\n\n◇出演者⑦\nフェアリーズ\r\nBLUE ENCOUNT\r\nBREAKERZ\r\nフレンズ\r\nFLOW\r\nふわふわ\r\nMAX\r\n眉村ちあき\r\n三浦祐太朗\r\n\n◇出演者⑧\n水樹奈々\r\nmilet\r\nmiwa\r\nモーニング娘。'19\r\n山本彩\r\nUNIONE\r\n緑黄色社会\r\nwacci\r\n（５０音順）\r\n\n◇公式ページ\n◇番組ＨＰ\r\nhttp://www.tbs.co.jp/ongakunohi/\r\n\n◇おことわり\n番組の内容と放送時間は変更になる可能性があります。",
  "start": 1563029100000,
  "end": 1563048000000,
  "seconds": 18900,
  "description": "音楽の日は第二部も引き続き「汗」をテーマに５時間１５分の生放送！様々なアーティストがメドレーやカバーに参加！汗が光る灼熱のステージをお届け！！",
  "extra": {
    "番組内容①": "第二部も引き続き「汗」をテーマに５時間１５分の生放送！「音楽の日」でしか見られないスペシャルメドレーやコラボレーションが盛りだくさん！！！",
    "番組内容②": "「ノンストップ灼熱うたリレー」では倖田來未の代表曲「キューティーハニー」から始まり、\r\nCHEMISTRY や HY、SHISHAMOなどが自身の大ヒットソングを熱く歌う！！\r\n",
    "番組内容③": "「夏うた全力カバーリレー」では日本人なら誰もが知っている夏の名曲をＡＫＢ４８や乃木坂４６ 、ゴールデンボンバー、そして人気急上昇中の s**t kingz （シットキングス）などが全力でカバー！\r\n",
    "番組内容④": "日本各地で活躍しているあのアーティストの皆さんも\r\nこの日のために赤坂に大集合し真夏の夜に熱いステージを披露！\r\n日本中の頑張る「汗」への応援歌をお届けします！\r\n",
    "出演者①": "AI\r\nIZ＊ONE\r\n藍井エイル\r\nAqours\r\n足立佳奈\r\nE-girls\r\n家入レオ\r\n内田雄馬\r\nウルフルズ\r\nAKB48\r\n",
    "出演者②": "HY\r\nA.B.C-Z\r\nSTU48\r\nエドガー・サリヴァン\r\nOnly this time\r\n木村カエラ\r\n倉木麻衣\r\nKREVA\r\nCHEMISTRY\r\n倖田來未\r\n",
    "出演者③": "ゴールデンボンバー\r\nSaucy Dog\r\nザ・コインロッカーズ\r\nThe Super Ball\r\nTHE RAMPAGE from EXILE TRIBE\r\n",
    "出演者④": "サンプラザ中野くん\r\nSEAMO\r\nGENERATIONS from EXILE TRIBE\r\nSHISHAMO\r\ns**t kingz\r\n",
    "出演者⑤": "ジャニーズWEST\r\nSuperfly\r\nスカイピース\r\n鈴木愛理\r\nChuning Candy\r\nD-51\r\nDRUM TAO\r\n中川翔子\r\n西川貴教\r\nnobodyknows+\r\n",
    "出演者⑥": "乃木坂46\r\nHOWL BE QUIET\r\nPerfume\r\nBALLISTIK BOYZ from EXILE TRIBE\r\nHAN-KUN\r\n日向坂46\r\nファンキー加藤\r\n",
    "出演者⑦": "フェアリーズ\r\nBLUE ENCOUNT\r\nBREAKERZ\r\nフレンズ\r\nFLOW\r\nふわふわ\r\nMAX\r\n眉村ちあき\r\n三浦祐太朗\r\n",
    "出演者⑧": "水樹奈々\r\nmilet\r\nmiwa\r\nモーニング娘。'19\r\n山本彩\r\nUNIONE\r\n緑黄色社会\r\nwacci\r\n（５０音順）\r\n",
    "公式ページ": "◇番組ＨＰ\r\nhttp://www.tbs.co.jp/ongakunohi/\r\n",
    "おことわり": "番組の内容と放送時間は変更になる可能性があります。\r\n"
  },
  "channel": {
    "type": "GR",
    "channel": "22",
    "name": "ＴＢＳ１",
    "id": "1i5727s",
    "sid": 1048,
    "nid": 32739,
    "hasLogoData": true,
    "n": 22
  },
  "subTitle": "汗",
  "episode": null,
  "flags": [
    "字",
    "デ"
  ]
}
